badbyte/VERSION
badbyte/__init__.py
badbyte/utils/__init__.py
badbyte/utils/colors.py
badbyte/utils/functions.py
badbyte-0.1.11.data/scripts/badbyte
badbyte-0.1.11.dist-info/LICENSE
badbyte-0.1.11.dist-info/METADATA
badbyte-0.1.11.dist-info/WHEEL
badbyte-0.1.11.dist-info/top_level.txt
badbyte-0.1.11.dist-info/RECORD
