Metadata-Version: 2.1
Name: badbyte
Version: 0.1.11
Summary: Deal with bad characters easily during exploit writing with badchars.
Home-page: https://github.com/C3l1n/badbyte
Author: Karol Jerzy Celiński
Author-email: karol@celin.pl
License: MIT
License-File: LICENSE
Requires-Dist: pwntools >=4.11.1
